dpsn_client/__init__.py
dpsn_client/client.py
dpsn_client/abi/__init__.py
dpsn_client/abi/contract_abi.json
utils/__init__.py
dpsn_client-1.0.3.dist-info/METADATA
dpsn_client-1.0.3.dist-info/WHEEL
dpsn_client-1.0.3.dist-info/top_level.txt
dpsn_client-1.0.3.dist-info/RECORD
