Metadata-Version: 2.4
Name: dpsn-client
Version: 1.0.3
Summary: DPSN MQTT client for managing topic subscriptions and publications
Author-email: Your Name <your.email@example.com>
Project-URL: Homepage, https://github.com/yourusername/dpsn-client
Classifier: Programming Language :: Python :: 3
Classifier: License :: OSI Approved :: MIT License
Classifier: Operating System :: OS Independent
Requires-Python: >=3.7
Requires-Dist: paho-mqtt>=1.6.1
Requires-Dist: web3>=6.0.0
Requires-Dist: events>=0.5
Requires-Dist: importlib_resources>=5.12; python_version < "3.9"
